aiit_sdk/__init__.py
aiit_sdk/algo.py
aiit_sdk/auth.py
aiit_sdk/log.py
aiit_sdk/page.py
aiit_sdk/response.py
aiit_sdk/storage.py
aiit_sdk/view.py
aiit_sdk-0.0.12.dist-info/LICENSE
aiit_sdk-0.0.12.dist-info/METADATA
aiit_sdk-0.0.12.dist-info/WHEEL
aiit_sdk-0.0.12.dist-info/top_level.txt
aiit_sdk-0.0.12.dist-info/RECORD
