Metadata-Version: 2.1
Name: aiit-sdk
Version: 0.0.12
Summary: A python sdk for AIIT OS
Home-page: http://192.168.140.202/unstructured-etl-group/aiit-sdk.git
Author: Guoqun Jin
Author-email: guoqun.jin@hotmail.com
License: GNU General Public License v3.0
Project-URL: Bug Tracker, http://192.168.140.202/unstructured-etl-group/aiit-sdk/-/issues
Classifier: Programming Language :: Python :: 3
Classifier: License :: OSI Approved :: MIT License
Classifier: Operating System :: OS Independent
Requires-Python: >=3.7
License-File: LICENSE
Requires-Dist: requests (>=2.25.1)
Requires-Dist: django-cacheops (>=5.1)
Requires-Dist: django-filter (>=21.1)
Requires-Dist: djangorestframework (>=3.12.2)
Requires-Dist: djangorestframework-simplejwt (>=4.6.0)
